{
  "recentFiles": [
    {
      "basename": "Diccionarios",
      "path": "Lecciones/Tipos de datos en Python/Diccionarios.md"
    },
    {
      "basename": "Set",
      "path": "Lecciones/Tipos de datos en Python/Set.md"
    },
    {
      "basename": "Tuplas",
      "path": "Lecciones/Tipos de datos en Python/Tuplas.md"
    },
    {
      "basename": "Listas",
      "path": "Lecciones/Tipos de datos en Python/Listas.md"
    },
    {
      "basename": "Funciones recursivas en python",
      "path": "Funciones recursivas en python.md"
    },
    {
      "basename": "Hola Mundo",
      "path": "Lecciones/Hola Mundo.md"
    },
    {
      "basename": "Doc. Laboratorio Cubo",
      "path": "POO/Doc. Laboratorio Cubo.md"
    },
    {
      "basename": "Conversiones",
      "path": "Lecciones/Hints/Conversiones.md"
    },
    {
      "basename": "Laboratorio Cubo",
      "path": "POO/code/Laboratorio Cubo.md"
    },
    {
      "basename": "Formatos en Obsidian",
      "path": "Formatos Obsidian/Formatos en Obsidian.md"
    },
    {
      "basename": "PRUEBA",
      "path": "Formatos Obsidian/PRUEBA.md"
    }
  ],
  "omittedPaths": [],
  "maxLength": null,
  "openType": "tab"
}