{
  "app:toggle-left-sidebar": [
    {
      "modifiers": [
        "Alt",
        "Mod"
      ],
      "key": "S"
    }
  ],
  "workspace:split-vertical": [
    {
      "modifiers": [
        "Alt",
        "Shift"
      ],
      "key": "L"
    }
  ],
  "workspace:split-horizontal": [
    {
      "modifiers": [
        "Alt",
        "Shift"
      ],
      "key": "K"
    }
  ],
  "editor:focus-top": [
    {
      "modifiers": [
        "Alt"
      ],
      "key": "J"
    }
  ],
  "editor:focus-bottom": [
    {
      "modifiers": [
        "Alt"
      ],
      "key": "K"
    }
  ],
  "editor:focus-left": [
    {
      "modifiers": [
        "Alt"
      ],
      "key": "H"
    }
  ],
  "editor:focus-right": [
    {
      "modifiers": [
        "Alt"
      ],
      "key": "L"
    }
  ]
}